{"type":"FeatureCollection","features":[{"type":"Feature","properties":{"name":"Restaurant"},"geometry":{"coordinates":[-64.83707531276163,45.028844474125265],"type":"Point"},"id":0},{"type":"Feature","properties":{"name":"League of Evil Villains"},"geometry":{"coordinates":[-64.83662153303563,45.02881488720769],"type":"Point"},"id":1},{"type":"Feature","properties":{"name":"Blake's Sushi"},"geometry":{"coordinates":[-64.83747191640002,45.02923045350889],"type":"Point"},"id":2},{"type":"Feature","properties":{"name":"Sam's Deli and Funeral Home"},"geometry":{"coordinates":[-64.83665791326308,45.02911951359647],"type":"Point"},"id":3}]}